{
    "25": {
        "wln": 3166,
        "wn": null,
        "name": "Necromancer by Halosty",
        "list": "RoyalRoad plan to read"
    },
    "98": {
        "wln": 3168,
        "wn": null,
        "name": "Fantasia",
        "list": "RoyalRoad plan to read"
    },
    "403": {
        "wln": 2406,
        "wn": null,
        "name": "Don't Fear the Reaper",
        "list": "RoyalRoad plan to read"
    },
    "527": {
        "wln": 142289,
        "wn": null,
        "name": "The Cleansing",
        "list": "RoyalRoad plan to read"
    },
    "544": {
        "wln": 2410,
        "wn": null,
        "name": "Master of All, Jack of None",
        "list": "RoyalRoad plan to read"
    },
    "717": {
        "wln": 2506,
        "wn": null,
        "name": "The Rude Time Stopper",
        "list": "stalled"
    },
    "807": {
        "wln": 2408,
        "wn": null,
        "name": "Spectral Regalia",
        "list": "RoyalRoad plan to read"
    },
    "1054": {
        "wln": 2468,
        "wn": null,
        "name": "Tales of the Blood Princess (expired version)",
        "list": "RoyalRoad plan to read"
    },
    "1439": {
        "wln": 2405,
        "wn": null,
        "name": "Forgotten Conqueror",
        "list": "RoyalRoad plan to read"
    },
    "1618": {
        "wln": 2801,
        "wn": null,
        "name": "Summoned Hero",
        "list": "on-hold"
    },
    "1729": {
        "wln": 2423,
        "wn": null,
        "name": "Change: New World",
        "list": "RoyalRoad plan to read"
    },
    "1992": {
        "wln": 2487,
        "wn": null,
        "name": "The New Journey of an Old Soul",
        "list": "RoyalRoad on-hold"
    },
    "2300": {
        "wln": 2522,
        "wn": null,
        "name": "The Parasite of knowledge",
        "list": "RoyalRoad plan to read"
    },
    "2720": {
        "wln": 142286,
        "wn": null,
        "name": "The Third Hero",
        "list": "RoyalRoad plan to read"
    },
    "2850": {
        "wln": 2860,
        "wn": null,
        "name": "Beyond?",
        "list": "RoyalRoad plan to read"
    },
    "3041": {
        "wln": 3202,
        "wn": null,
        "name": "New Game Plus",
        "list": "RoyalRoad plan to read"
    },
    "3253": {
        "wln": 8458,
        "wn": null,
        "name": "Hardcore OP-ness",
        "list": "RoyalRoad on-hold"
    },
    "3619": {
        "wln": 32444,
        "wn": null,
        "name": "Silver Death",
        "list": "RoyalRoad stalled"
    },
    "3666": {
        "wln": 32381,
        "wn": null,
        "name": "I was reincarnated as a Magic Academy!",
        "list": "reading"
    },
    "3667": {
        "wln": 32382,
        "wn": null,
        "name": "100 Luck and the Dragon Tamer Skill!",
        "list": "reading"
    },
    "3754": {
        "wln": 32528,
        "wn": null,
        "name": "Andur's Oneshot collection",
        "list": "RoyalRoad plan to read"
    },
    "3966": {
        "wln": 32671,
        "wn": null,
        "name": "Lord Shadow",
        "list": "QIDIAN plan to read original"
    },
    "4023": {
        "wln": 32702,
        "wn": null,
        "name": "Of Monsters \u0026 Men",
        "list": "RoyalRoad plan to read"
    },
    "4144": {
        "wln": 33197,
        "wn": null,
        "name": "Slave Tyrant",
        "list": "RoyalRoad plan to read"
    },
    "4242": {
        "wln": 33459,
        "wn": null,
        "name": "World Seed",
        "list": "RoyalRoad plan to read"
    },
    "4293": {
        "wln": 35956,
        "wn": null,
        "name": "The Iron Teeth: A Goblin's Tale",
        "list": "RoyalRoad plan to read"
    },
    "4629": {
        "wln": 34514,
        "wn": null,
        "name": "The Daily Diary of a Mushroom",
        "list": "RoyalRoad plan to read"
    },
    "4676": {
        "wln": 34389,
        "wn": null,
        "name": "How Do You QA Test a Tsundere Android!?",
        "list": "RoyalRoad plan to read"
    },
    "4697": {
        "wln": 34881,
        "wn": null,
        "name": "Sole Survivor",
        "list": "RoyalRoad"
    },
    "4699": {
        "wln": 34524,
        "wn": null,
        "name": "Old: The Dark Inheritor",
        "list": "RoyalRoad"
    },
    "5029": {
        "wln": 35113,
        "wn": null,
        "name": "The Blue Mage Raised by Dragons",
        "list": "RoyalRoad"
    },
    "5132": {
        "wln": 35242,
        "wn": null,
        "name": "(On Hold) Regarding my time being a God, it was fun",
        "list": "RoyalRoad plan to read"
    },
    "5288": {
        "wln": 35418,
        "wn": null,
        "name": "How to Avoid Death on a Daily Basis",
        "list": "RoyalRoad plan to read"
    },
    "5696": {
        "wln": 35818,
        "wn": null,
        "name": "God's Trials",
        "list": "RoyalRoad plan to read"
    },
    "5701": {
        "wln": 35819,
        "wn": null,
        "name": "Savage Divinity",
        "list": "RoyalRoad"
    },
    "6639": {
        "wln": 42897,
        "wn": null,
        "name": "Rise of the Fallen (Tyranny)",
        "list": "RoyalRoad plan to read"
    },
    "6694": {
        "wln": 42866,
        "wn": null,
        "name": "The path to ascension",
        "list": "RoyalRoad plan to read"
    },
    "6752": {
        "wln": 42756,
        "wn": null,
        "name": "Lament of the Fallen",
        "list": "RoyalRoad plan to read"
    },
    "6773": {
        "wln": 42700,
        "wn": null,
        "name": "The Vespidian",
        "list": "RoyalRoad plan to read"
    },
    "7183": {
        "wln": 43638,
        "wn": null,
        "name": "Crashed Into Fantasy",
        "list": "RoyalRoad plan to read"
    },
    "7297": {
        "wln": 44054,
        "wn": null,
        "name": "Apathy (Jathias)",
        "list": "RoyalRoad plan to read"
    },
    "7509": {
        "wln": 44152,
        "wn": null,
        "name": "World Keeper",
        "list": "RoyalRoad plan to read"
    },
    "7578": {
        "wln": 44214,
        "wn": null,
        "name": "Demon's Journey",
        "list": "RoyalRoad"
    },
    "7599": {
        "wln": 44250,
        "wn": null,
        "name": "How To Tame Your Princess",
        "list": "RoyalRoad plan to read"
    },
    "8100": {
        "wln": 47081,
        "wn": null,
        "name": "Binary Soul",
        "list": "RoyalRoad"
    },
    "8220": {
        "wln": 78250,
        "wn": null,
        "name": "Mythran's Master Of All - Continued (Completed!)",
        "list": "RoyalRoad plan to read"
    },
    "8463": {
        "wln": 49612,
        "wn": null,
        "name": "The Arcane Emperor",
        "list": "RoyalRoad"
    },
    "8894": {
        "wln": 50921,
        "wn": null,
        "name": "Everybody Loves Large Chests",
        "list": "RoyalRoad plan to read"
    },
    "9500": {
        "wln": 53949,
        "wn": null,
        "name": "The Eagle's Flight",
        "list": "RoyalRoad plan to read"
    },
    "9885": {
        "wln": 141980,
        "wn": null,
        "name": "Star Justice: Eye of the Tiger",
        "list": "RoyalRoad plan to read"
    },
    "10211": {
        "wln": 55938,
        "wn": null,
        "name": "Necrotourists",
        "list": "RoyalRoad"
    },
    "10381": {
        "wln": 56545,
        "wn": null,
        "name": "Maou Shoujo Magical Chaos",
        "list": "RoyalRoad"
    },
    "10515": {
        "wln": 135467,
        "wn": null,
        "name": "World Keeper Au [Dead - Awaiting Rewrite]",
        "list": "duplicates"
    },
    "10703": {
        "wln": 56879,
        "wn": null,
        "name": "The Godking's Legacy",
        "list": "RoyalRoad plan to read"
    },
    "10748": {
        "wln": 57027,
        "wn": null,
        "name": "Junkyard Magician",
        "list": "RoyalRoad"
    },
    "10756": {
        "wln": 57636,
        "wn": null,
        "name": "New: The Dark Inheritor",
        "list": "RoyalRoad"
    },
    "11209": {
        "wln": 57391,
        "wn": null,
        "name": "The Legend of Randidly Ghosthound",
        "list": "RoyalRoad on-hold"
    },
    "11397": {
        "wln": 57637,
        "wn": null,
        "name": "The Dao of Magic",
        "list": "RoyalRoad plan to read"
    },
    "11588": {
        "wln": 57840,
        "wn": null,
        "name": "The Void Wolf",
        "list": "RoyalRoad plan to read"
    },
    "11620": {
        "wln": 58106,
        "wn": null,
        "name": "Red Mantis and Avenger Doll",
        "list": "RoyalRoad"
    },
    "12024": {
        "wln": 58556,
        "wn": null,
        "name": "The new world",
        "list": "RoyalRoad plan to read"
    },
    "12878": {
        "wln": 59496,
        "wn": null,
        "name": "Small Chests Are Fine Too",
        "list": "RoyalRoad plan to read"
    },
    "13187": {
        "wln": 59649,
        "wn": null,
        "name": "Silver Death (Re)",
        "list": "RoyalRoad stalled"
    },
    "14023": {
        "wln": 60640,
        "wn": null,
        "name": "Blood Creed",
        "list": "QIDIAN plan to read original"
    },
    "14070": {
        "wln": 60595,
        "wn": null,
        "name": "Master Of Everything (Completed?)",
        "list": "RoyalRoad plan to read"
    },
    "14167": {
        "wln": 60663,
        "wn": null,
        "name": "Metaworld Chronicles",
        "list": "RoyalRoad plan to read"
    },
    "14396": {
        "wln": 60905,
        "wn": null,
        "name": "The Snake Report",
        "list": "RoyalRoad"
    },
    "14558": {
        "wln": 61294,
        "wn": null,
        "name": "Crystal Shards Online - A LitRPG Series",
        "list": "RoyalRoad plan to read"
    },
    "15459": {
        "wln": 61818,
        "wn": null,
        "name": "The Daily Diary of a VRMMO-playing Dragon",
        "list": "RoyalRoad plan to read"
    },
    "15538": {
        "wln": 61911,
        "wn": null,
        "name": "Displaced",
        "list": "RoyalRoad"
    },
    "15934": {
        "wln": 62196,
        "wn": null,
        "name": "Monster Yurisume: My lesbian life with Monster Girls",
        "list": "RoyalRoad"
    },
    "15935": {
        "wln": 90542,
        "wn": null,
        "name": "There is no Epic Loot, Only Puns",
        "list": "duplicates"
    },
    "16449": {
        "wln": 62685,
        "wn": null,
        "name": "Curse of the Kat (Dropped)",
        "list": "RoyalRoad plan to read"
    },
    "16717": {
        "wln": 62951,
        "wn": null,
        "name": "The Salamanders",
        "list": "RoyalRoad"
    },
    "16913": {
        "wln": 63190,
        "wn": null,
        "name": "Mind Reading Isn't Cheating",
        "list": "RoyalRoad"
    },
    "16946": {
        "wln": 63197,
        "wn": null,
        "name": "Azarinth Healer",
        "list": "RoyalRoad"
    },
    "17207": {
        "wln": 63456,
        "wn": null,
        "name": "Cursed Armor Reincarnation",
        "list": "RoyalRoad"
    },
    "17868": {
        "wln": 66111,
        "wn": null,
        "name": "Mother of Monsters",
        "list": "RoyalRoad plan to read"
    },
    "18307": {
        "wln": 63699,
        "wn": null,
        "name": "Chronicles of the Weakest Wind Mage",
        "list": "QIDIAN plan to read original"
    },
    "18567": {
        "wln": 43114,
        "wn": null,
        "name": "Pandemonium",
        "list": "RoyalRoad plan to read"
    },
    "20177": {
        "wln": 69758,
        "wn": null,
        "name": "The Misplaced Dungeon",
        "list": "RoyalRoad"
    },
    "20243": {
        "wln": 70419,
        "wn": null,
        "name": "The Demon Lord's Lover",
        "list": "RoyalRoad"
    },
    "20434": {
        "wln": 71274,
        "wn": null,
        "name": "The Other Side of the Bed - Half-Stuck in a Fantasy World",
        "list": "RoyalRoad plan to read"
    },
    "20568": {
        "wln": 71587,
        "wn": null,
        "name": "Tree of Aeons (An isekai story)",
        "list": "RoyalRoad"
    },
    "20780": {
        "wln": 71570,
        "wn": null,
        "name": "What Do You Mean All Dungeons Are Girls!!!?",
        "list": "ScribbleHub"
    },
    "21188": {
        "wln": 74196,
        "wn": null,
        "name": "Forge of Destiny",
        "list": "RoyalRoad plan to read"
    },
    "21220": {
        "wln": 34875,
        "wn": null,
        "name": "Mother of Learning",
        "list": "RoyalRoad completed"
    },
    "21322": {
        "wln": 77223,
        "wn": null,
        "name": "RE: Trailer Trash",
        "list": "RoyalRoad plan to read"
    },
    "21323": {
        "wln": 110712,
        "wn": null,
        "name": "Twilight Kingdom",
        "list": "RoyalRoad"
    },
    "21361": {
        "wln": 74909,
        "wn": null,
        "name": "Skyclad",
        "list": "RoyalRoad plan to read"
    },
    "21450": {
        "wln": 75379,
        "wn": null,
        "name": "The Power of Formations",
        "list": "RoyalRoad plan to read"
    },
    "21581": {
        "wln": 75971,
        "wn": null,
        "name": "The Reborn Runesmith",
        "list": "RoyalRoad plan to read"
    },
    "21817": {
        "wln": 83659,
        "wn": null,
        "name": "The Prince of Cats",
        "list": "RoyalRoad plan to read"
    },
    "22019": {
        "wln": 77757,
        "wn": null,
        "name": "Undermind",
        "list": "RoyalRoad"
    },
    "22115": {
        "wln": 78190,
        "wn": null,
        "name": "I don't want to be the Hive Queen",
        "list": "RoyalRoad"
    },
    "22518": {
        "wln": 2768,
        "wn": null,
        "name": "Chrysalis",
        "list": "RoyalRoad"
    },
    "22533": {
        "wln": 114382,
        "wn": null,
        "name": "A Rational Zombie",
        "list": "RoyalRoad plan to read"
    },
    "22653": {
        "wln": 82024,
        "wn": null,
        "name": "Supervillainy and Other Poor Career Choices",
        "list": "RoyalRoad"
    },
    "22681": {
        "wln": 80555,
        "wn": null,
        "name": "Monster Integration",
        "list": "QIDIAN plan to read original"
    },
    "22848": {
        "wln": 86198,
        "wn": null,
        "name": "Post Human",
        "list": "RoyalRoad"
    },
    "23055": {
        "wln": 87289,
        "wn": null,
        "name": "It's the Healer's Life for Me",
        "list": "RoyalRoad"
    },
    "23240": {
        "wln": 88690,
        "wn": null,
        "name": "Dark Wizard's Case. LitRPG series",
        "list": "RoyalRoad plan to read"
    },
    "23978": {
        "wln": 89719,
        "wn": null,
        "name": "Age of Teras: Monster Evolution",
        "list": "QIDIAN plan to read"
    },
    "24241": {
        "wln": 91203,
        "wn": null,
        "name": "Sundered Soul: A cultivation Wuxia\/Xianxia novel",
        "list": "RoyalRoad plan to read"
    },
    "24360": {
        "wln": 96334,
        "wn": null,
        "name": "Oracle's Path",
        "list": "RoyalRoad plan to read"
    },
    "24412": {
        "wln": 93970,
        "wn": null,
        "name": "Dragon Knight Prophecy",
        "list": "RoyalRoad plan to read"
    },
    "24709": {
        "wln": 94313,
        "wn": null,
        "name": "Defiance of the Fall",
        "list": "RoyalRoad plan to read"
    },
    "24734": {
        "wln": 81573,
        "wn": null,
        "name": "Our Goddess",
        "list": "RoyalRoad"
    },
    "24762": {
        "wln": 112670,
        "wn": null,
        "name": "The First Born",
        "list": "RoyalRoad plan to read"
    },
    "24853": {
        "wln": 101099,
        "wn": null,
        "name": "Adventures of the Goldthirst Company",
        "list": "RoyalRoad"
    },
    "25082": {
        "wln": 97112,
        "wn": null,
        "name": "Blue Core",
        "list": "RoyalRoad"
    },
    "25161": {
        "wln": 97967,
        "wn": null,
        "name": "The Reincarnated Master Craftsman Just Wants To Live A Peaceful Life.",
        "list": "ScribbleHub"
    },
    "25225": {
        "wln": 98528,
        "wn": null,
        "name": "Delve",
        "list": "RoyalRoad on-hold"
    },
    "25275": {
        "wln": 131565,
        "wn": null,
        "name": "Forgotten (Rick Scott)",
        "list": "RoyalRoad plan to read"
    },
    "25293": {
        "wln": 110924,
        "wn": null,
        "name": "Web of Worlds: Empire. GUARD. Book 1. litRPG series",
        "list": "RoyalRoad"
    },
    "25299": {
        "wln": 98792,
        "wn": null,
        "name": "Misadventures of a Rampaging Demon",
        "list": "RoyalRoad stalled"
    },
    "25561": {
        "wln": 101587,
        "wn": null,
        "name": "Rupegia",
        "list": "RoyalRoad"
    },
    "25562": {
        "wln": 101588,
        "wn": null,
        "name": "Though the Heavens Should Fall",
        "list": "RoyalRoad plan to read"
    },
    "25568": {
        "wln": 97804,
        "wn": null,
        "name": "My Dungeon Life: Rise of the Slave Harem",
        "list": "RoyalRoad"
    },
    "26127": {
        "wln": 107247,
        "wn": null,
        "name": "A Beginner's Guide to Napping, Sunbathing, and Slaughtering Your Prey",
        "list": "RoyalRoad plan to read"
    },
    "26149": {
        "wln": 107979,
        "wn": null,
        "name": "Skybound",
        "list": "RoyalRoad plan to read"
    },
    "26279": {
        "wln": 107405,
        "wn": null,
        "name": "Living as I please, As a loli Demon King",
        "list": "ScribbleHub"
    },
    "26284": {
        "wln": 143456,
        "wn": null,
        "name": "Seven (Riese)",
        "list": "RoyalRoad"
    },
    "26294": {
        "wln": 107213,
        "wn": null,
        "name": "He Who Fights With Monsters",
        "list": "RoyalRoad"
    },
    "26534": {
        "wln": 107604,
        "wn": null,
        "name": "Vainqueur the Dragon",
        "list": "RoyalRoad"
    },
    "26674": {
        "wln": 107165,
        "wn": null,
        "name": "Cursed Reincarnation",
        "list": "RoyalRoad"
    },
    "26675": {
        "wln": 107801,
        "wn": null,
        "name": "A Journey of Black and Red",
        "list": "RoyalRoad"
    },
    "26727": {
        "wln": 107713,
        "wn": null,
        "name": "Ar'Kendrithyst",
        "list": "RoyalRoad"
    },
    "26749": {
        "wln": 107742,
        "wn": null,
        "name": "I Just Wanted To Die But Instead I Became Immortal",
        "list": "RoyalRoad"
    },
    "27213": {
        "wln": 113848,
        "wn": null,
        "name": "Against the Heaven's Will",
        "list": "RoyalRoad plan to read"
    },
    "27263": {
        "wln": 110709,
        "wn": null,
        "name": "The Infinite Labyrinth",
        "list": "RoyalRoad"
    },
    "27287": {
        "wln": 108342,
        "wn": null,
        "name": "Heather the Necromancer",
        "list": "RoyalRoad"
    },
    "27325": {
        "wln": 115382,
        "wn": null,
        "name": "Infinite Realm Monsters Legends",
        "list": "RoyalRoad plan to read"
    },
    "27426": {
        "wln": 108642,
        "wn": null,
        "name": "Class Neutral: Stranger is Coming",
        "list": "RoyalRoad"
    },
    "27495": {
        "wln": 113806,
        "wn": null,
        "name": "To Play With Magic",
        "list": "RoyalRoad"
    },
    "27523": {
        "wln": 127341,
        "wn": null,
        "name": "An Old Man's Journey",
        "list": "RoyalRoad plan to read"
    },
    "27757": {
        "wln": 113779,
        "wn": null,
        "name": "Shut Up: You Nymphomaniac Evil Sword",
        "list": "RoyalRoad plan to read"
    },
    "27872": {
        "wln": 108931,
        "wn": null,
        "name": "Confessions of the Magpie Wizard",
        "list": "RoyalRoad plan to read"
    },
    "27981": {
        "wln": 109217,
        "wn": null,
        "name": "The Soul Force Saga",
        "list": "RoyalRoad plan to read"
    },
    "28004": {
        "wln": 112909,
        "wn": null,
        "name": "Kalar's continent",
        "list": "QIDIAN stalled"
    },
    "28254": {
        "wln": 109277,
        "wn": null,
        "name": "Nanocultivation Chronicles: Trials of Lilijoy",
        "list": "RoyalRoad"
    },
    "28307": {
        "wln": 109221,
        "wn": null,
        "name": "The Zombie Knight Saga",
        "list": "RoyalRoad"
    },
    "28385": {
        "wln": 59514,
        "wn": null,
        "name": "Kairos: Gears Against Gods",
        "list": "RoyalRoad plan to read"
    },
    "28578": {
        "wln": 109430,
        "wn": null,
        "name": "Unfathomable Senior",
        "list": "RoyalRoad"
    },
    "28656": {
        "wln": 109754,
        "wn": null,
        "name": "Dawn Weaver - a tale of Dragon Riders",
        "list": "duplicates"
    },
    "28970": {
        "wln": 109873,
        "wn": null,
        "name": "Hands Held in the Snow",
        "list": "RoyalRoad plan to read"
    },
    "28995": {
        "wln": 112342,
        "wn": null,
        "name": "Warfare's Ultimate Frontier",
        "list": "RoyalRoad plan to read"
    },
    "29425": {
        "wln": 110373,
        "wn": null,
        "name": "A Dragon Idol's Reincarnation Tale",
        "list": "RoyalRoad"
    },
    "29507": {
        "wln": 110493,
        "wn": null,
        "name": "Curse of Clwyd",
        "list": "RoyalRoad"
    },
    "29540": {
        "wln": 110575,
        "wn": null,
        "name": "Evil Overlord: The Makening",
        "list": "RoyalRoad plan to read"
    },
    "29669": {
        "wln": 110649,
        "wn": null,
        "name": "Love Crafted",
        "list": "RoyalRoad completed"
    },
    "29807": {
        "wln": 110760,
        "wn": null,
        "name": "Princess",
        "list": "RoyalRoad completed"
    },
    "29936": {
        "wln": 90014,
        "wn": null,
        "name": "The First Magician",
        "list": "RoyalRoad"
    },
    "29995": {
        "wln": 111171,
        "wn": null,
        "name": "The Sleeper",
        "list": "RoyalRoad plan to read"
    },
    "30131": {
        "wln": 111252,
        "wn": null,
        "name": "Seaborn",
        "list": "RoyalRoad plan to read"
    },
    "30216": {
        "wln": 111209,
        "wn": null,
        "name": "Headpats",
        "list": "RoyalRoad"
    },
    "30321": {
        "wln": 71502,
        "wn": null,
        "name": "UB",
        "list": "duplicates"
    },
    "30380": {
        "wln": 112421,
        "wn": null,
        "name": "Jayke Cipher",
        "list": "RoyalRoad"
    },
    "30396": {
        "wln": 112210,
        "wn": null,
        "name": "Ideascape: An Adventure LitRPG",
        "list": "RoyalRoad"
    },
    "30605": {
        "wln": 81989,
        "wn": null,
        "name": "Magnus",
        "list": "RoyalRoad on-hold"
    },
    "30650": {
        "wln": 111540,
        "wn": null,
        "name": "Evil Goddess System",
        "list": "QIDIAN plan to read original"
    },
    "30737": {
        "wln": 111631,
        "wn": null,
        "name": "The Humble Life of a Skill Trainer",
        "list": "RoyalRoad"
    },
    "30932": {
        "wln": 113408,
        "wn": null,
        "name": "The Hero Raised by a Monster",
        "list": "RoyalRoad plan to read"
    },
    "31062": {
        "wln": 112288,
        "wn": null,
        "name": "Saga of the Cosmic Heroes",
        "list": "RoyalRoad plan to read"
    },
    "31429": {
        "wln": 112336,
        "wn": null,
        "name": "Cinnamon Bun",
        "list": "RoyalRoad"
    },
    "31474": {
        "wln": 112321,
        "wn": null,
        "name": "Magic-Smithing",
        "list": "RoyalRoad"
    },
    "31514": {
        "wln": 112555,
        "wn": null,
        "name": "The Menocht Loop",
        "list": "RoyalRoad plan to read"
    },
    "32067": {
        "wln": 115553,
        "wn": null,
        "name": "Never Die Twice",
        "list": "RoyalRoad"
    },
    "32123": {
        "wln": 116138,
        "wn": null,
        "name": "Just a Bystander",
        "list": "RoyalRoad"
    },
    "32139": {
        "wln": 117962,
        "wn": null,
        "name": "Interdimensional Garbage Merchant",
        "list": "RoyalRoad"
    },
    "32334": {
        "wln": 115783,
        "wn": null,
        "name": "Technically Abroad",
        "list": "RoyalRoad"
    },
    "32375": {
        "wln": 60335,
        "wn": null,
        "name": "The Void King.",
        "list": "RoyalRoad plan to read"
    },
    "32551": {
        "wln": 119192,
        "wn": null,
        "name": "Oak: A Tree's Quest",
        "list": "RoyalRoad"
    },
    "32576": {
        "wln": 119029,
        "wn": null,
        "name": "Villager Three",
        "list": "RoyalRoad"
    },
    "32615": {
        "wln": 116456,
        "wn": null,
        "name": "Rend",
        "list": "RoyalRoad"
    },
    "32908": {
        "wln": 120338,
        "wn": null,
        "name": "The Calamity of a Reborn Witch",
        "list": "RoyalRoad"
    },
    "33003": {
        "wln": 116777,
        "wn": null,
        "name": "My Cerberus Girlfriend",
        "list": "RoyalRoad plan to read"
    },
    "33013": {
        "wln": 119333,
        "wn": null,
        "name": "Letters From a Lost Bird",
        "list": "RoyalRoad"
    },
    "33020": {
        "wln": 116733,
        "wn": null,
        "name": "Blessed Time",
        "list": "RoyalRoad plan to read"
    },
    "33054": {
        "wln": 116880,
        "wn": null,
        "name": "Soulforged Dungeoneer",
        "list": "RoyalRoad plan to read"
    },
    "33277": {
        "wln": 117088,
        "wn": null,
        "name": "Soul Forging",
        "list": "RoyalRoad plan to read"
    },
    "33283": {
        "wln": 117392,
        "wn": null,
        "name": "Aoi",
        "list": "RoyalRoad plan to read"
    },
    "33295": {
        "wln": 117274,
        "wn": null,
        "name": "Summon Imp!",
        "list": "RoyalRoad"
    },
    "33363": {
        "wln": 117803,
        "wn": null,
        "name": "Bounty Cats",
        "list": "RoyalRoad plan to read"
    },
    "33378": {
        "wln": 118806,
        "wn": null,
        "name": "I Became a [Biologist] in a Fantasy World!",
        "list": "RoyalRoad plan to read"
    },
    "33386": {
        "wln": 120036,
        "wn": null,
        "name": "Soul Flames",
        "list": "RoyalRoad plan to read"
    },
    "33461": {
        "wln": 119523,
        "wn": null,
        "name": "This Young Master is not Cannon Fodder",
        "list": "RoyalRoad plan to read"
    },
    "33600": {
        "wln": 119007,
        "wn": null,
        "name": "Stray Cat Strut",
        "list": "RoyalRoad"
    },
    "33801": {
        "wln": 118863,
        "wn": null,
        "name": "This Quest is Bullshit",
        "list": "RoyalRoad"
    },
    "33844": {
        "wln": 57046,
        "wn": null,
        "name": "The Runesmith",
        "list": "RoyalRoad"
    },
    "33988": {
        "wln": 118049,
        "wn": null,
        "name": "Pink Mage",
        "list": "RoyalRoad"
    },
    "34030": {
        "wln": 119103,
        "wn": null,
        "name": "Artificial Jelly",
        "list": "RoyalRoad stalled"
    },
    "34372": {
        "wln": 120120,
        "wn": null,
        "name": "The world of fantasy (naman khetarpal)",
        "list": "RoyalRoad plan to read"
    },
    "34388": {
        "wln": 119016,
        "wn": null,
        "name": "Mindshifter: The Mind War",
        "list": "RoyalRoad"
    },
    "34409": {
        "wln": 130232,
        "wn": null,
        "name": "A Cat Is Fine Too",
        "list": "RoyalRoad plan to read"
    },
    "34473": {
        "wln": 118775,
        "wn": null,
        "name": "Shade Touched",
        "list": "RoyalRoad plan to read"
    },
    "34644": {
        "wln": 108849,
        "wn": null,
        "name": "Guildmaster",
        "list": "RoyalRoad plan to read"
    },
    "34753": {
        "wln": 119358,
        "wn": null,
        "name": "The 13th Essence",
        "list": "RoyalRoad"
    },
    "34777": {
        "wln": 120139,
        "wn": null,
        "name": "Hilda Finds a Home",
        "list": "RoyalRoad plan to read"
    },
    "34798": {
        "wln": 111530,
        "wn": null,
        "name": "Melas",
        "list": "RoyalRoad stalled"
    },
    "35017": {
        "wln": 119575,
        "wn": null,
        "name": "Invasion - A Nanomachine Magical World LitRPG Adventure",
        "list": "RoyalRoad stalled"
    },
    "35212": {
        "wln": 119984,
        "wn": null,
        "name": "Return of the Tower Conqueror",
        "list": "RoyalRoad plan to read"
    },
    "35289": {
        "wln": 119970,
        "wn": null,
        "name": "Ito Ai: A New Dawn",
        "list": "QIDIAN original"
    },
    "35391": {
        "wln": 120373,
        "wn": null,
        "name": "DreadWolf",
        "list": "ScribbleHub"
    },
    "35549": {
        "wln": 120505,
        "wn": null,
        "name": "Prophecy Approved Companion",
        "list": "RoyalRoad on-hold"
    },
    "35774": {
        "wln": 127577,
        "wn": null,
        "name": "The Girl With The Crimson Eyes",
        "list": "RoyalRoad plan to read"
    },
    "35942": {
        "wln": 127755,
        "wn": null,
        "name": "Weakest Demon Queen Reincarnation: I Became a Living Armor?!",
        "list": "RoyalRoad plan to read"
    },
    "35958": {
        "wln": 127831,
        "wn": null,
        "name": "Fluff",
        "list": "RoyalRoad"
    },
    "36049": {
        "wln": 128397,
        "wn": null,
        "name": "The Primal Hunter",
        "list": "RoyalRoad plan to read"
    },
    "36051": {
        "wln": 127902,
        "wn": null,
        "name": "Memories of the Fall",
        "list": "RoyalRoad plan to read"
    },
    "36065": {
        "wln": 128026,
        "wn": null,
        "name": "Sylver Seeker",
        "list": "RoyalRoad"
    },
    "36272": {
        "wln": 128416,
        "wn": null,
        "name": "The Necromancer in Magic School",
        "list": "RoyalRoad"
    },
    "36299": {
        "wln": 128229,
        "wn": null,
        "name": "Beneath the Dragoneye Moons",
        "list": "RoyalRoad"
    },
    "36371": {
        "wln": 128403,
        "wn": null,
        "name": "Respawn Condition: Trash Mob",
        "list": "RoyalRoad"
    },
    "36391": {
        "wln": 128301,
        "wn": null,
        "name": "Master Necromancer",
        "list": "RoyalRoad plan to read"
    },
    "36650": {
        "wln": 128990,
        "wn": null,
        "name": "The Stained Tower",
        "list": "RoyalRoad"
    },
    "36659": {
        "wln": 129032,
        "wn": null,
        "name": "His Majesty's Immortal Academy",
        "list": "RoyalRoad plan to read"
    },
    "36726": {
        "wln": 128782,
        "wn": null,
        "name": "A Path to Magic",
        "list": "RoyalRoad"
    },
    "36735": {
        "wln": 129103,
        "wn": null,
        "name": "The Perfect Run",
        "list": "RoyalRoad plan to read"
    },
    "36904": {
        "wln": 129608,
        "wn": null,
        "name": "How can I save the world if I'm no longer the hero?",
        "list": "RoyalRoad"
    },
    "36983": {
        "wln": 129507,
        "wn": null,
        "name": "Tower of Somnus",
        "list": "RoyalRoad"
    },
    "37016": {
        "wln": 129517,
        "wn": null,
        "name": "Earth's Alpha Prime",
        "list": "QIDIAN plan to read original"
    },
    "37103": {
        "wln": 129392,
        "wn": null,
        "name": "Reroll",
        "list": "RoyalRoad stalled"
    },
    "37231": {
        "wln": 128991,
        "wn": null,
        "name": "A Lonely Dungeon",
        "list": "RoyalRoad completed"
    },
    "37251": {
        "wln": 129558,
        "wn": null,
        "name": "Dead Tired",
        "list": "RoyalRoad"
    },
    "37333": {
        "wln": 129566,
        "wn": null,
        "name": "Dungeon Item Shop",
        "list": "RoyalRoad on-hold"
    },
    "37346": {
        "wln": 129630,
        "wn": null,
        "name": "Dungeon of Seasons",
        "list": "RoyalRoad"
    },
    "37391": {
        "wln": 128405,
        "wn": null,
        "name": "I'm in a Monster Girl World (MGW)",
        "list": "ScribbleHub"
    },
    "37626": {
        "wln": 130167,
        "wn": null,
        "name": "Summoned as a Ghost in another world",
        "list": "RoyalRoad"
    },
    "37719": {
        "wln": 130141,
        "wn": null,
        "name": "Emmy And Me",
        "list": "RoyalRoad plan to read"
    },
    "37951": {
        "wln": 130399,
        "wn": null,
        "name": "RE: Monarch",
        "list": "RoyalRoad plan to read"
    },
    "38230": {
        "wln": 128076,
        "wn": null,
        "name": "Rise of the Weakest Summoner",
        "list": "RoyalRoad"
    },
    "38240": {
        "wln": 129191,
        "wn": null,
        "name": "Realm of Monsters",
        "list": "RoyalRoad plan to read"
    },
    "38292": {
        "wln": 130768,
        "wn": null,
        "name": "An Unbound Soul",
        "list": "RoyalRoad"
    },
    "38306": {
        "wln": 130853,
        "wn": null,
        "name": "Chronicles of the Exalted Sun Child",
        "list": "RoyalRoad"
    },
    "38361": {
        "wln": 131041,
        "wn": null,
        "name": "Restaurant Core",
        "list": "RoyalRoad"
    },
    "38397": {
        "wln": 131053,
        "wn": null,
        "name": "Dungeon Core Abi",
        "list": "RoyalRoad"
    },
    "38860": {
        "wln": 131556,
        "wn": null,
        "name": "Abyssal Road Trip",
        "list": "RoyalRoad"
    },
    "38944": {
        "wln": 131709,
        "wn": null,
        "name": "Darius Supreme",
        "list": "QIDIAN original"
    },
    "39090": {
        "wln": 131842,
        "wn": null,
        "name": "Reborn! A Thief's Greed in a Fantasy World",
        "list": "RoyalRoad stalled"
    },
    "39193": {
        "wln": 131967,
        "wn": null,
        "name": "Requiem of the Sea",
        "list": "RoyalRoad plan to read"
    },
    "39307": {
        "wln": 132103,
        "wn": null,
        "name": "A fine octet of legs",
        "list": "RoyalRoad"
    },
    "39375": {
        "wln": 132403,
        "wn": null,
        "name": "New Game +",
        "list": "RoyalRoad plan to read"
    },
    "39408": {
        "wln": 132273,
        "wn": null,
        "name": "Beware Of Chicken",
        "list": "RoyalRoad"
    },
    "39473": {
        "wln": 135258,
        "wn": null,
        "name": "Watchers",
        "list": "RoyalRoad plan to read"
    },
    "39738": {
        "wln": 132701,
        "wn": null,
        "name": "Shade and Flow",
        "list": "RoyalRoad"
    },
    "39751": {
        "wln": 132824,
        "wn": null,
        "name": "Fates Parallel (A Xianxia\/Wuxia Inspired Cultivation Story)",
        "list": "RoyalRoad plan to read"
    },
    "39903": {
        "wln": 134331,
        "wn": null,
        "name": "AK \\u2013 The Alchemy Kingdom",
        "list": "duplicates"
    },
    "40062": {
        "wln": 134120,
        "wn": null,
        "name": "Path of the Dragon Mage: Exiled",
        "list": "duplicates"
    },
    "40193": {
        "wln": 134291,
        "wn": null,
        "name": "Poison God's Heritage",
        "list": "QIDIAN on-hold"
    },
    "40237": {
        "wln": 133372,
        "wn": null,
        "name": "The Agartha Loop",
        "list": "RoyalRoad"
    },
    "40265": {
        "wln": 133726,
        "wn": null,
        "name": "Dungeon I\/O (Crafting)",
        "list": "RoyalRoad plan to read"
    },
    "40275": {
        "wln": 70010,
        "wn": null,
        "name": "Life Hunter",
        "list": "QIDIAN original"
    },
    "40277": {
        "wln": 136750,
        "wn": null,
        "name": "A Hero's Song",
        "list": "RoyalRoad plan to read"
    },
    "40285": {
        "wln": 133698,
        "wn": null,
        "name": "Morcster Chef",
        "list": "RoyalRoad plan to read"
    },
    "40295": {
        "wln": 131420,
        "wn": null,
        "name": "The Harvester",
        "list": "RoyalRoad"
    },
    "40373": {
        "wln": 133809,
        "wn": null,
        "name": "Vigor Mortis",
        "list": "RoyalRoad"
    },
    "40503": {
        "wln": 134080,
        "wn": null,
        "name": "The Obsidian Core",
        "list": "RoyalRoad plan to read"
    },
    "40601": {
        "wln": 133901,
        "wn": null,
        "name": "Dear Spellbook (Link to rewrite in blurb)",
        "list": "RoyalRoad stalled"
    },
    "40659": {
        "wln": 134195,
        "wn": null,
        "name": "The Jinni and The Isekai",
        "list": "RoyalRoad plan to read"
    },
    "40700": {
        "wln": 137446,
        "wn": null,
        "name": "Reincarnation Station: Death, Cake and Friendship",
        "list": "RoyalRoad plan to read"
    },
    "40888": {
        "wln": 135424,
        "wn": null,
        "name": "The Great Core's Paradox",
        "list": "RoyalRoad"
    },
    "40914": {
        "wln": 134804,
        "wn": null,
        "name": "Battlemaster's Gambit A LITRPG Monstergirl Harem Adventure",
        "list": "RoyalRoad"
    },
    "40920": {
        "wln": 134370,
        "wn": null,
        "name": "The Path of Ascension",
        "list": "RoyalRoad plan to read"
    },
    "40929": {
        "wln": 137261,
        "wn": null,
        "name": "Gemstone Goblins (LitRPG)",
        "list": "RoyalRoad plan to read"
    },
    "40966": {
        "wln": 134386,
        "wn": null,
        "name": "Living Armor",
        "list": "RoyalRoad plan to read"
    },
    "40998": {
        "wln": 134554,
        "wn": null,
        "name": "A Friendly Voidling",
        "list": "RoyalRoad completed"
    },
    "41012": {
        "wln": 96995,
        "wn": null,
        "name": "New Earth",
        "list": "RoyalRoad"
    },
    "41033": {
        "wln": 134559,
        "wn": null,
        "name": "Kairos: A Greek Myth LitRPG",
        "list": "RoyalRoad plan to read"
    },
    "41112": {
        "wln": 134638,
        "wn": null,
        "name": "Cosmic Bulldozing Team",
        "list": "RoyalRoad stalled"
    },
    "41147": {
        "wln": 135083,
        "wn": null,
        "name": "Of Monstergirls and Men",
        "list": "RoyalRoad plan to read"
    },
    "41198": {
        "wln": 134818,
        "wn": null,
        "name": "Jack of All",
        "list": "RoyalRoad"
    },
    "41423": {
        "wln": 135126,
        "wn": null,
        "name": "Lever Action",
        "list": "RoyalRoad"
    },
    "41434": {
        "wln": 135289,
        "wn": null,
        "name": "Immortality.Upload (LitRPG: Athanasia - Book 1)",
        "list": "RoyalRoad plan to read"
    },
    "41450": {
        "wln": 135227,
        "wn": null,
        "name": "Myrr: Reincarnated Timemage Assassin",
        "list": "RoyalRoad"
    },
    "41477": {
        "wln": 136609,
        "wn": null,
        "name": "Truth Seeker [OLD VERSION]",
        "list": "RoyalRoad"
    },
    "41511": {
        "wln": 76403,
        "wn": null,
        "name": "Lost In Translation",
        "list": "RoyalRoad plan to read"
    },
    "41521": {
        "wln": 135346,
        "wn": null,
        "name": "A Budding Scientist in a Fantasy World",
        "list": "RoyalRoad"
    },
    "41522": {
        "wln": 135292,
        "wn": null,
        "name": "Ogre Tyrant",
        "list": "RoyalRoad"
    },
    "41591": {
        "wln": 135715,
        "wn": null,
        "name": "A Journey in Darkness",
        "list": "RoyalRoad"
    },
    "41599": {
        "wln": 135989,
        "wn": null,
        "name": "Tian",
        "list": "duplicates"
    },
    "41618": {
        "wln": 135600,
        "wn": null,
        "name": "Mark of the Fool",
        "list": "RoyalRoad plan to read"
    },
    "41764": {
        "wln": 135527,
        "wn": null,
        "name": "A Demon's Journey (Jmarcs.)",
        "list": "RoyalRoad plan to read"
    },
    "41772": {
        "wln": 142421,
        "wn": null,
        "name": "The Isekai will be Livestreamed",
        "list": "RoyalRoad"
    },
    "41780": {
        "wln": 135988,
        "wn": null,
        "name": "Thick as Thieves",
        "list": "RoyalRoad"
    },
    "41805": {
        "wln": 135653,
        "wn": null,
        "name": "Somebody Stop Her",
        "list": "RoyalRoad on-hold"
    },
    "41836": {
        "wln": 136498,
        "wn": null,
        "name": "Evil Eye: Hexcaller",
        "list": "RoyalRoad stalled"
    },
    "41853": {
        "wln": 131840,
        "wn": null,
        "name": "ReBorn Necro",
        "list": "ScribbleHub"
    },
    "41862": {
        "wln": 135704,
        "wn": null,
        "name": "Slime Cafe",
        "list": "RoyalRoad stalled"
    },
    "41881": {
        "wln": 135813,
        "wn": null,
        "name": "Wizard's Tower",
        "list": "RoyalRoad"
    },
    "41961": {
        "wln": 131853,
        "wn": null,
        "name": "Royal Princess of Blood",
        "list": "RoyalRoad"
    },
    "42012": {
        "wln": 140043,
        "wn": null,
        "name": "The Isekai Police aka Earths Advocates",
        "list": "RoyalRoad plan to read"
    },
    "42124": {
        "wln": 135895,
        "wn": null,
        "name": "An Unwilling Monster",
        "list": "RoyalRoad"
    },
    "42202": {
        "wln": 135959,
        "wn": null,
        "name": "The Way Ahead",
        "list": "RoyalRoad"
    },
    "42226": {
        "wln": 136106,
        "wn": null,
        "name": "Fox's Tongue and Kirin's Bone",
        "list": "RoyalRoad"
    },
    "42270": {
        "wln": 136068,
        "wn": null,
        "name": "Master of the System",
        "list": "RoyalRoad plan to read"
    },
    "42370": {
        "wln": 136117,
        "wn": null,
        "name": "This Slimy Melting Heart",
        "list": "RoyalRoad"
    },
    "42385": {
        "wln": 136131,
        "wn": null,
        "name": "An Outcast In Another World",
        "list": "RoyalRoad"
    },
    "42433": {
        "wln": 136569,
        "wn": null,
        "name": "Peculiar Soul",
        "list": "RoyalRoad"
    },
    "42441": {
        "wln": 136182,
        "wn": null,
        "name": "Elder Cultivator",
        "list": "RoyalRoad"
    },
    "42463": {
        "wln": 136307,
        "wn": null,
        "name": "The Grand Game",
        "list": "RoyalRoad stalled"
    },
    "42492": {
        "wln": 136198,
        "wn": null,
        "name": "De-Monster",
        "list": "RoyalRoad"
    },
    "42521": {
        "wln": 137358,
        "wn": null,
        "name": "The Reincarnation of Alysara [Progression LitRPG]",
        "list": "RoyalRoad"
    },
    "42579": {
        "wln": 3374,
        "wn": null,
        "name": "Phantasm",
        "list": "RoyalRoad"
    },
    "42630": {
        "wln": 136336,
        "wn": null,
        "name": "A Dream of Wings and Flame",
        "list": "RoyalRoad"
    },
    "42673": {
        "wln": 136543,
        "wn": null,
        "name": "The Bewitching Chaos Ghost System",
        "list": "QIDIAN plan to read original"
    },
    "42685": {
        "wln": 136534,
        "wn": null,
        "name": "Elania, Arachne in a different world",
        "list": "RoyalRoad"
    },
    "42728": {
        "wln": 136375,
        "wn": null,
        "name": "Tales of an Unlikely Wizard Isekai LitRPG",
        "list": "RoyalRoad stalled"
    },
    "42788": {
        "wln": 136511,
        "wn": null,
        "name": "Reincarnated as a Nightwalker",
        "list": "RoyalRoad stalled"
    },
    "42833": {
        "wln": 136144,
        "wn": null,
        "name": "Abyssal Knight in the Modern World",
        "list": "RoyalRoad plan to read"
    },
    "42986": {
        "wln": 136659,
        "wn": null,
        "name": "I Have Infinite Skill Points in the Apocalypse",
        "list": "RoyalRoad plan to read"
    },
    "43013": {
        "wln": 136860,
        "wn": null,
        "name": "All These Tentacles",
        "list": "RoyalRoad plan to read"
    },
    "43036": {
        "wln": 136729,
        "wn": null,
        "name": "Magical Girl Kari: Apocalypse System (Mahou Shoujo LitRPG)",
        "list": "RoyalRoad"
    },
    "43180": {
        "wln": 137101,
        "wn": null,
        "name": "I'm Not a Competitive Necromancer",
        "list": "RoyalRoad"
    },
    "43181": {
        "wln": 137029,
        "wn": null,
        "name": "The Hedge Wizard",
        "list": "RoyalRoad"
    },
    "43271": {
        "wln": 137025,
        "wn": null,
        "name": "Dungeon Core Chat Room.",
        "list": "RoyalRoad"
    },
    "43318": {
        "wln": 137412,
        "wn": null,
        "name": "The Butcher of Gadobhra",
        "list": "RoyalRoad"
    },
    "43377": {
        "wln": 137112,
        "wn": null,
        "name": "The Way of Wrought Earth, or: My Tale of Rebirth as a Mostly Inanimate Rock",
        "list": "RoyalRoad"
    },
    "43381": {
        "wln": 140992,
        "wn": null,
        "name": "The Core: The First Guest (Book 1 of 3)",
        "list": "WattPad"
    },
    "43490": {
        "wln": 137307,
        "wn": null,
        "name": "Healing Dungeon",
        "list": "RoyalRoad"
    },
    "43582": {
        "wln": 137274,
        "wn": null,
        "name": "Apotheosis - The Grand Dungeon of Kess",
        "list": "RoyalRoad"
    },
    "43592": {
        "wln": 137281,
        "wn": null,
        "name": "A Sense for magic",
        "list": "RoyalRoad"
    },
    "43638": {
        "wln": 137310,
        "wn": null,
        "name": "Dragons Dilemma",
        "list": "duplicates"
    },
    "43673": {
        "wln": 137361,
        "wn": null,
        "name": "Morcster Chef: Reckoning",
        "list": "RoyalRoad plan to read"
    },
    "43714": {
        "wln": 137523,
        "wn": null,
        "name": "Mana Soul",
        "list": "RoyalRoad"
    },
    "43875": {
        "wln": 137617,
        "wn": null,
        "name": "Memories Of The Void [A Monster Evolution LitRPG]",
        "list": "RoyalRoad plan to read"
    },
    "43887": {
        "wln": 138206,
        "wn": null,
        "name": "Cultivator vs. System",
        "list": "RoyalRoad plan to read"
    },
    "43934": {
        "wln": 138802,
        "wn": null,
        "name": "Realmshaker: Giant Progression LitRPG",
        "list": "RoyalRoad stalled"
    },
    "43958": {
        "wln": 137716,
        "wn": null,
        "name": "Breaker of Horizons",
        "list": "RoyalRoad"
    },
    "43974": {
        "wln": 137704,
        "wn": null,
        "name": "Melody of Mana",
        "list": "RoyalRoad"
    },
    "44024": {
        "wln": 144734,
        "wn": null,
        "name": "Misadventures Incorporated",
        "list": "RoyalRoad"
    },
    "44111": {
        "wln": 129065,
        "wn": null,
        "name": "Flight of a Villainess",
        "list": "RoyalRoad plan to read"
    },
    "44132": {
        "wln": 137834,
        "wn": null,
        "name": "The Calamitous Bob",
        "list": "RoyalRoad"
    },
    "44146": {
        "wln": 138354,
        "wn": null,
        "name": "My Ex-Girlfriend is the Strongest Guild Master and I'm the Weakest!",
        "list": "RoyalRoad plan to read"
    },
    "44205": {
        "wln": 137915,
        "wn": null,
        "name": "I Was Summoned To Have Tea With The Demon Lord [Rewrite]",
        "list": "RoyalRoad plan to read"
    },
    "44229": {
        "wln": 137802,
        "wn": null,
        "name": "My Best Friend is an Eldritch Horror",
        "list": "RoyalRoad"
    },
    "44272": {
        "wln": 139878,
        "wn": null,
        "name": "The Great, Unstoppable, Irreplaceable Alexander",
        "list": "RoyalRoad plan to read"
    },
    "44330": {
        "wln": 137935,
        "wn": null,
        "name": "Sin-Eater",
        "list": "RoyalRoad plan to read"
    },
    "44463": {
        "wln": 138165,
        "wn": null,
        "name": "The Hallowed War",
        "list": "RoyalRoad plan to read"
    },
    "44516": {
        "wln": 138590,
        "wn": null,
        "name": "Obligate of a Self-Ordained Sorcerer",
        "list": "RoyalRoad"
    },
    "44541": {
        "wln": 138160,
        "wn": null,
        "name": "Heart of Dorkness",
        "list": "RoyalRoad"
    },
    "44589": {
        "wln": 138121,
        "wn": null,
        "name": "Reborn From the Cosmos",
        "list": "ScribbleHub"
    },
    "44716": {
        "wln": 138664,
        "wn": null,
        "name": "Drinker of the Yew: A Necromancer's Tale",
        "list": "RoyalRoad plan to read"
    },
    "44887": {
        "wln": 138810,
        "wn": null,
        "name": "Blood Shaper",
        "list": "RoyalRoad"
    },
    "44929": {
        "wln": 137449,
        "wn": null,
        "name": "Etudie Perpetuity: Genius Student in Another World",
        "list": "RoyalRoad"
    },
    "45003": {
        "wln": 141131,
        "wn": null,
        "name": "Warlock's Gate [DROPPED]",
        "list": "RoyalRoad plan to read"
    },
    "45048": {
        "wln": 138698,
        "wn": null,
        "name": "Hive Minds Give Good Hugs",
        "list": "RoyalRoad"
    },
    "45050": {
        "wln": 138913,
        "wn": null,
        "name": "Snow Flames",
        "list": "RoyalRoad plan to read"
    },
    "45090": {
        "wln": 141567,
        "wn": null,
        "name": "Tentacles, loot boxes and apocalypse [monster evolution story]",
        "list": "RoyalRoad stalled"
    },
    "45136": {
        "wln": 139062,
        "wn": null,
        "name": "The King's Soul: A LitRPG Wuxia Novel",
        "list": "RoyalRoad plan to read"
    },
    "45139": {
        "wln": 143802,
        "wn": null,
        "name": "Always Together",
        "list": "RoyalRoad plan to read"
    },
    "45229": {
        "wln": 139193,
        "wn": null,
        "name": "Epic Blade - a LitRPG Adventure",
        "list": "RoyalRoad"
    },
    "45279": {
        "wln": 139279,
        "wn": null,
        "name": "The Knightly Elven... Spider? [GL, litRPG]",
        "list": "RoyalRoad"
    },
    "45434": {
        "wln": 139257,
        "wn": null,
        "name": "Echoes of the Tribulation: An Historical Apocalypse LitRPG Series.",
        "list": "RoyalRoad plan to read"
    },
    "45493": {
        "wln": 139304,
        "wn": null,
        "name": "Liches Get Stitches",
        "list": "RoyalRoad"
    },
    "45534": {
        "wln": 139283,
        "wn": null,
        "name": "This Used to be About Dungeons",
        "list": "RoyalRoad"
    },
    "45610": {
        "wln": 139385,
        "wn": null,
        "name": "My Dream World Is A Gacha Nightmare",
        "list": "RoyalRoad plan to read"
    },
    "45725": {
        "wln": 139620,
        "wn": null,
        "name": "Her Golemancer Girlfriend",
        "list": "RoyalRoad"
    },
    "45898": {
        "wln": 139970,
        "wn": null,
        "name": "Blood Demon's Retirement",
        "list": "RoyalRoad"
    },
    "46047": {
        "wln": 140134,
        "wn": null,
        "name": "Everyone's a Catgirl!",
        "list": "RoyalRoad"
    },
    "46114": {
        "wln": 140315,
        "wn": null,
        "name": "The Big Bad Wolf",
        "list": "RoyalRoad"
    },
    "46201": {
        "wln": 140399,
        "wn": null,
        "name": "Useless Strength In The Modern World",
        "list": "RoyalRoad plan to read"
    },
    "46292": {
        "wln": 142464,
        "wn": null,
        "name": "[Dropped ver, read desc] Solo Player Rebirth!",
        "list": "RoyalRoad stalled"
    },
    "46319": {
        "wln": 141041,
        "wn": null,
        "name": "Speedrunning the Multiverse",
        "list": "RoyalRoad"
    },
    "46378": {
        "wln": 141013,
        "wn": null,
        "name": "Frameshift",
        "list": "RoyalRoad"
    },
    "46394": {
        "wln": 140488,
        "wn": null,
        "name": "The Demon's Rapture",
        "list": "RoyalRoad"
    },
    "46417": {
        "wln": 140450,
        "wn": null,
        "name": "The Core: The Hive Daughter (Book 2 of 3)",
        "list": "RoyalRoad"
    },
    "46602": {
        "wln": 141561,
        "wn": null,
        "name": "Give my lily pad back. (currently undergoing editing.)",
        "list": "RoyalRoad"
    },
    "46638": {
        "wln": 140724,
        "wn": null,
        "name": "Steamforged Sorcery [A Steampunk LitRPG]",
        "list": "RoyalRoad"
    },
    "46709": {
        "wln": 141706,
        "wn": null,
        "name": "Enduring Good",
        "list": "RoyalRoad"
    },
    "46830": {
        "wln": 143824,
        "wn": null,
        "name": "Tales of Demons and Dragons - An Apocalyptic Xianxia!",
        "list": "RoyalRoad"
    },
    "46849": {
        "wln": 141618,
        "wn": null,
        "name": "Trickster's Song [A LitRPG Portal Fantasy]",
        "list": "RoyalRoad"
    },
    "46850": {
        "wln": 141564,
        "wn": null,
        "name": "War Queen (Writathon)",
        "list": "RoyalRoad"
    },
    "46868": {
        "wln": 141033,
        "wn": null,
        "name": "Reincarnated into a Time-Loop Dungeon as a LVL100 Catgirl Chef!",
        "list": "RoyalRoad"
    },
    "46901": {
        "wln": 141208,
        "wn": null,
        "name": "The Last Orellen",
        "list": "RoyalRoad"
    },
    "46942": {
        "wln": 141569,
        "wn": null,
        "name": "The New Horizon [GL LitRPG]",
        "list": "RoyalRoad"
    },
    "47017": {
        "wln": 141289,
        "wn": null,
        "name": "Infrasound Berserker",
        "list": "RoyalRoad"
    },
    "47018": {
        "wln": 141538,
        "wn": null,
        "name": "Saga of Cosmic Journey",
        "list": "RoyalRoad plan to read"
    },
    "47030": {
        "wln": 141541,
        "wn": null,
        "name": "Tori Transmigrated",
        "list": "RoyalRoad"
    },
    "47118": {
        "wln": 141547,
        "wn": null,
        "name": "Dungeon Core? Nah, I Think I'll Just Get Super-Wealthy Instead",
        "list": "RoyalRoad"
    },
    "47175": {
        "wln": 142867,
        "wn": null,
        "name": "Sage of Humanity",
        "list": "RoyalRoad"
    },
    "47372": {
        "wln": 153317,
        "wn": null,
        "name": "The Accidental Summoning",
        "list": "RoyalRoad"
    },
    "47434": {
        "wln": 142237,
        "wn": null,
        "name": "Apocalypse Parenting",
        "list": "RoyalRoad"
    },
    "47529": {
        "wln": 144136,
        "wn": null,
        "name": "The Heist at Cordia Aquarium",
        "list": "RoyalRoad plan to read"
    },
    "47541": {
        "wln": 141951,
        "wn": null,
        "name": "The Trials of Bethany",
        "list": "RoyalRoad"
    },
    "47557": {
        "wln": 100731,
        "wn": null,
        "name": "Underland",
        "list": "RoyalRoad"
    },
    "47619": {
        "wln": 142008,
        "wn": null,
        "name": "Shattered Realms",
        "list": "RoyalRoad stalled"
    },
    "47621": {
        "wln": 142811,
        "wn": null,
        "name": "Saltworld: An Apocalypse LitRPG",
        "list": "RoyalRoad"
    },
    "47631": {
        "wln": 142091,
        "wn": null,
        "name": "The Supernormal",
        "list": "RoyalRoad"
    },
    "47826": {
        "wln": 142466,
        "wn": null,
        "name": "Millennial Mage (A Slice of Life, Progression Fantasy)",
        "list": "RoyalRoad"
    },
    "47903": {
        "wln": 142454,
        "wn": null,
        "name": "Under Wicked Sky",
        "list": "RoyalRoad plan to read"
    },
    "47914": {
        "wln": 142685,
        "wn": null,
        "name": "The Journey of a God: Book 1",
        "list": "RoyalRoad"
    },
    "47959": {
        "wln": 142434,
        "wn": null,
        "name": "Unliving",
        "list": "RoyalRoad"
    },
    "47965": {
        "wln": 142556,
        "wn": null,
        "name": "Ebony Chitin - Adventures of The Hive",
        "list": "RoyalRoad"
    },
    "47979": {
        "wln": 142498,
        "wn": null,
        "name": "Warrior, Wizard, Demon Queen?",
        "list": "RoyalRoad"
    },
    "47982": {
        "wln": 143540,
        "wn": null,
        "name": "Tunnel Rat",
        "list": "RoyalRoad"
    },
    "47995": {
        "wln": 142601,
        "wn": null,
        "name": "Memoirs of Your Local Small-time Villainess",
        "list": "RoyalRoad"
    },
    "47997": {
        "wln": 142455,
        "wn": null,
        "name": "Overkill (RavensDagger)",
        "list": "duplicates"
    },
    "48008": {
        "wln": 142383,
        "wn": null,
        "name": "Dreamers Ten-Tea-Cle Cafe",
        "list": "RoyalRoad"
    },
    "48017": {
        "wln": 142804,
        "wn": null,
        "name": "TWIG - The System Can't Save Me, But It Can't Stop Me Either [a gamelit-portal-fantasy-poem by eric river]",
        "list": "RoyalRoad plan to read"
    },
    "48056": {
        "wln": 142688,
        "wn": null,
        "name": "I Am Not Chaotic Evil",
        "list": "RoyalRoad"
    },
    "48101": {
        "wln": 142552,
        "wn": null,
        "name": "Crafting a Golem",
        "list": "RoyalRoad plan to read"
    },
    "48311": {
        "wln": 142735,
        "wn": null,
        "name": "Weaponsmith : [A crafting litRPG]",
        "list": "RoyalRoad"
    },
    "48346": {
        "wln": 142743,
        "wn": null,
        "name": "A Girl and Her Food",
        "list": "RoyalRoad"
    },
    "48364": {
        "wln": 144869,
        "wn": null,
        "name": "Braindead - A Zombie LitRPG",
        "list": "RoyalRoad"
    },
    "48397": {
        "wln": 142908,
        "wn": null,
        "name": "Solo Player Rebirth! [A LitRPG Fantasy series]",
        "list": "RoyalRoad"
    },
    "48398": {
        "wln": 140967,
        "wn": null,
        "name": "Programmable Magic",
        "list": "ScribbleHub"
    },
    "48460": {
        "wln": 143055,
        "wn": null,
        "name": "The Reluctant Court Wizard",
        "list": "RoyalRoad"
    },
    "48535": {
        "wln": 143104,
        "wn": null,
        "name": "The Ruins of Magincia",
        "list": "RoyalRoad"
    },
    "48558": {
        "wln": 143108,
        "wn": null,
        "name": "Pocket Healer",
        "list": "RoyalRoad"
    },
    "48641": {
        "wln": 141039,
        "wn": null,
        "name": "Former Undead Transmigrated to become Villainess's Butler",
        "list": "RoyalRoad"
    },
    "48690": {
        "wln": 147847,
        "wn": null,
        "name": "ALL HOLLOW",
        "list": "RoyalRoad"
    },
    "48754": {
        "wln": 143408,
        "wn": null,
        "name": "Tokens and Towers (A LitRPG\/GameLit Adventure)",
        "list": "RoyalRoad"
    },
    "48900": {
        "wln": 143734,
        "wn": null,
        "name": "Skyrates?!",
        "list": "duplicates"
    },
    "48951": {
        "wln": 143833,
        "wn": null,
        "name": "A (Not So) Simple Fetch Quest",
        "list": "RoyalRoad plan to read"
    },
    "48969": {
        "wln": 143836,
        "wn": null,
        "name": "Jackal Among Snakes",
        "list": "duplicates"
    },
    "48970": {
        "wln": 145899,
        "wn": null,
        "name": "In Dying Starlight: A Cyborg Sci-Fi Adventure",
        "list": "RoyalRoad"
    },
    "49031": {
        "wln": 144707,
        "wn": null,
        "name": "At The Precipice",
        "list": "RoyalRoad"
    },
    "49032": {
        "wln": 143815,
        "wn": null,
        "name": "Trace",
        "list": "RoyalRoad"
    },
    "49033": {
        "wln": 143816,
        "wn": null,
        "name": "Mother of Learning: The AU Chapters",
        "list": "RoyalRoad"
    },
    "49141": {
        "wln": 143975,
        "wn": null,
        "name": "Royal Blood",
        "list": "RoyalRoad"
    },
    "49256": {
        "wln": 144202,
        "wn": null,
        "name": "The Guardian (The Legend of Little Red Riding Hood \u0026 Her Wolf)",
        "list": "RoyalRoad"
    },
    "49284": {
        "wln": 144128,
        "wn": null,
        "name": "Casual Heroing",
        "list": "RoyalRoad"
    },
    "49300": {
        "wln": 144207,
        "wn": null,
        "name": "Descent of the Arcane",
        "list": "RoyalRoad"
    },
    "49319": {
        "wln": 144213,
        "wn": null,
        "name": "Roots and Steel",
        "list": "RoyalRoad"
    },
    "49390": {
        "wln": 144173,
        "wn": null,
        "name": "First Line of Defense, Book 1: Welcome to the Universe.",
        "list": "duplicates"
    },
    "49434": {
        "wln": 32022,
        "wn": null,
        "name": "The First Mage",
        "list": "RoyalRoad"
    },
    "49541": {
        "wln": 144046,
        "wn": null,
        "name": "Magical Giants: The Life of Zmeya",
        "list": "ScribbleHub"
    },
    "49679": {
        "wln": 146657,
        "wn": null,
        "name": "Cruxborne Legends",
        "list": "RoyalRoad"
    },
    "49722": {
        "wln": 145073,
        "wn": null,
        "name": "Technomagica",
        "list": "RoyalRoad"
    },
    "49879": {
        "wln": 144906,
        "wn": null,
        "name": "Paranoid Mage",
        "list": "RoyalRoad"
    },
    "49881": {
        "wln": 136050,
        "wn": null,
        "name": "Dear Spellbook (rewrite)",
        "list": "RoyalRoad"
    },
    "49926": {
        "wln": 145053,
        "wn": null,
        "name": "Wandering Web",
        "list": "RoyalRoad"
    },
    "49962": {
        "wln": 147850,
        "wn": null,
        "name": "Sect Leader",
        "list": "RoyalRoad"
    },
    "50005": {
        "wln": 108024,
        "wn": null,
        "name": "Cheaters Always Win",
        "list": "RoyalRoad"
    },
    "50007": {
        "wln": 145345,
        "wn": null,
        "name": "ECLIPSE: A Complete Fantasy Novelette",
        "list": "RoyalRoad plan to read"
    },
    "50034": {
        "wln": 145012,
        "wn": null,
        "name": "Planetary Orbital Weapon - An orbital-particle-cannon based LitRPG",
        "list": "RoyalRoad"
    },
    "50070": {
        "wln": 145170,
        "wn": null,
        "name": "Altura's Defiance [ A Transmigrated into a Villainess LitRPG with Kingdom Building, MC befriending and Xianxia Politics]",
        "list": "RoyalRoad"
    },
    "50138": {
        "wln": 145151,
        "wn": null,
        "name": "Damien Nightshade The Villainous Vampire",
        "list": "RoyalRoad"
    },
    "50242": {
        "wln": 145273,
        "wn": null,
        "name": "Grand Magus: Reincarnated with the Engineer Element",
        "list": "ScribbleHub"
    },
    "50243": {
        "wln": 146270,
        "wn": null,
        "name": "Mark of the Crijik",
        "list": "RoyalRoad"
    },
    "50249": {
        "wln": 145254,
        "wn": null,
        "name": "Path of the Hive Queen",
        "list": "RoyalRoad"
    },
    "50278": {
        "wln": 145857,
        "wn": null,
        "name": "The Eternal Seeker Saga",
        "list": "RoyalRoad"
    },
    "50282": {
        "wln": 145341,
        "wn": null,
        "name": "I Died and Got Summoned to Another World as a WHAT?!?!",
        "list": "RoyalRoad"
    },
    "50399": {
        "wln": 146228,
        "wn": null,
        "name": "The Princess of Malik'Dar (Warriors of Sword \u0026 Sorcery)",
        "list": "RoyalRoad plan to read"
    },
    "50434": {
        "wln": 145526,
        "wn": null,
        "name": "Protagonist: The Whims of Gods",
        "list": "RoyalRoad"
    },
    "50519": {
        "wln": 145812,
        "wn": null,
        "name": "Eldest: Awakening After the End",
        "list": "RoyalRoad"
    },
    "50539": {
        "wln": 145639,
        "wn": null,
        "name": "The Perfect Run: Bad Runs",
        "list": "RoyalRoad plan to read"
    },
    "50542": {
        "wln": 145598,
        "wn": null,
        "name": "Third Apocalypse - A Generic Reincarnation Epic LitRPG Fantasy Adventure With a System",
        "list": "RoyalRoad"
    },
    "50553": {
        "wln": 145896,
        "wn": null,
        "name": "Double-Blind: A Modern LITRPG",
        "list": "RoyalRoad"
    },
    "50608": {
        "wln": 145721,
        "wn": null,
        "name": "Kneel: A Guide to Demonic Ascension",
        "list": "RoyalRoad"
    },
    "50619": {
        "wln": 145750,
        "wn": null,
        "name": "Apocalypse King: Progression System LitRPG",
        "list": "RoyalRoad"
    },
    "50675": {
        "wln": 146120,
        "wn": null,
        "name": "Quest of the Seal Bearers - Book 1: The Warriors Return",
        "list": "RoyalRoad"
    },
    "50738": {
        "wln": 146059,
        "wn": null,
        "name": "BuyMort: Rise of the Windowpuncher - How I Became the Accidental Warlord of Arizona. Apocalyptic GameLit",
        "list": "RoyalRoad plan to read"
    },
    "50784": {
        "wln": 63413,
        "wn": null,
        "name": "The Oath of Oblivion",
        "list": "RoyalRoad"
    },
    "50901": {
        "wln": 146114,
        "wn": null,
        "name": "Broken Interface",
        "list": "RoyalRoad"
    },
    "51167": {
        "wln": 146406,
        "wn": null,
        "name": "I died and reincarnated as a ghost",
        "list": "RoyalRoad"
    },
    "51175": {
        "wln": 146793,
        "wn": null,
        "name": "Spirits Awakening",
        "list": "duplicates"
    },
    "51335": {
        "wln": 146897,
        "wn": null,
        "name": "PathOgen [Forge Your Own Path] Reader Interactive",
        "list": "RoyalRoad plan to read"
    },
    "51358": {
        "wln": 146935,
        "wn": null,
        "name": "Dungeon Devotee",
        "list": "RoyalRoad"
    },
    "51364": {
        "wln": 131510,
        "wn": null,
        "name": "Where It All Began",
        "list": "RoyalRoad plan to read"
    },
    "51368": {
        "wln": 146952,
        "wn": null,
        "name": "Feast or Famine",
        "list": "RoyalRoad"
    },
    "51389": {
        "wln": 146740,
        "wn": null,
        "name": "Valkyrie's Dawn",
        "list": "RoyalRoad"
    },
    "51435": {
        "wln": 148211,
        "wn": null,
        "name": "There Will Be Dragons Here",
        "list": "RoyalRoad"
    },
    "51439": {
        "wln": 150389,
        "wn": null,
        "name": "Odd Heroes",
        "list": "RoyalRoad plan to read"
    },
    "51552": {
        "wln": 145832,
        "wn": null,
        "name": "The Hunchback's Reluctant Bride",
        "list": "RoyalRoad plan to read"
    },
    "51870": {
        "wln": 147347,
        "wn": null,
        "name": "Mark of Time: A LitRPG Timeloop",
        "list": "RoyalRoad"
    },
    "51877": {
        "wln": 147332,
        "wn": null,
        "name": "Apocalypse Unleashed: A LitRPG Story",
        "list": "RoyalRoad"
    },
    "51947": {
        "wln": 147446,
        "wn": null,
        "name": "The Strongest Spirit Form, I Was Summoned From The Future",
        "list": "RoyalRoad plan to read"
    },
    "52194": {
        "wln": 132294,
        "wn": null,
        "name": "Oathbound",
        "list": "RoyalRoad"
    },
    "52394": {
        "wln": 148095,
        "wn": null,
        "name": "Scraprats",
        "list": "RoyalRoad"
    },
    "52459": {
        "wln": 151435,
        "wn": null,
        "name": "Good Guy Necromancer",
        "list": "RoyalRoad"
    },
    "52501": {
        "wln": 148533,
        "wn": null,
        "name": "The Mother of Monsters",
        "list": "RoyalRoad"
    },
    "52503": {
        "wln": 148225,
        "wn": null,
        "name": "Godslayers",
        "list": "RoyalRoad"
    },
    "52582": {
        "wln": 148728,
        "wn": null,
        "name": "Wish upon the Stars",
        "list": "RoyalRoad plan to read"
    },
    "52626": {
        "wln": 148389,
        "wn": null,
        "name": "Sunflower : [A sunflower based litRPG]",
        "list": "RoyalRoad"
    },
    "52639": {
        "wln": 148565,
        "wn": null,
        "name": "Edge Cases",
        "list": "RoyalRoad"
    },
    "52702": {
        "wln": 149112,
        "wn": null,
        "name": "The Grimoire is Not Complete! [A Magical LitRPG Adventure!]",
        "list": "RoyalRoad"
    },
    "52713": {
        "wln": 148511,
        "wn": null,
        "name": "Free Lances",
        "list": "duplicates"
    },
    "52739": {
        "wln": 148529,
        "wn": null,
        "name": "The Plagued Rat",
        "list": "RoyalRoad"
    },
    "52765": {
        "wln": 148634,
        "wn": null,
        "name": "The Programmer's Dungeon [Progression, LitRPG]",
        "list": "RoyalRoad"
    },
    "52835": {
        "wln": 149272,
        "wn": null,
        "name": "Nomad Healer",
        "list": "RoyalRoad"
    },
    "52842": {
        "wln": 148733,
        "wn": null,
        "name": "Warmage: A Progression Fantasy",
        "list": "RoyalRoad"
    },
    "52854": {
        "wln": 148744,
        "wn": null,
        "name": "An Unwavering Craftsman",
        "list": "RoyalRoad"
    },
    "52872": {
        "wln": 148851,
        "wn": null,
        "name": "Journey Into The Abyss: A Progression Fantasy",
        "list": "RoyalRoad"
    },
    "52883": {
        "wln": 148769,
        "wn": null,
        "name": "Living as a Demon",
        "list": "RoyalRoad plan to read"
    },
    "52903": {
        "wln": 148748,
        "wn": null,
        "name": "A Dream Harem Life Built With Superior Firepower",
        "list": "RoyalRoad"
    },
    "52915": {
        "wln": 148867,
        "wn": null,
        "name": "The Lost Archon",
        "list": "RoyalRoad"
    },
    "52968": {
        "wln": 148853,
        "wn": null,
        "name": "Weird Magic",
        "list": "RoyalRoad"
    },
    "52992": {
        "wln": 148947,
        "wn": null,
        "name": "I Choose Violence. A Imperium- Isekai LITRPG Portal Harem Fantasy",
        "list": "RoyalRoad"
    },
    "53086": {
        "wln": 149057,
        "wn": null,
        "name": "Mana breaker - A litRPG Epic",
        "list": "RoyalRoad"
    },
    "53109": {
        "wln": 148972,
        "wn": null,
        "name": "Journey of a Thousand Shadows - An Isekai Story",
        "list": "RoyalRoad"
    },
    "53184": {
        "wln": 149343,
        "wn": null,
        "name": "The Elusive Human, So Often Forgotten [Progression Fantasy]",
        "list": "RoyalRoad"
    },
    "53291": {
        "wln": 149278,
        "wn": null,
        "name": "Witches \u0026 Knights \u0026 Unicorn Fights",
        "list": "RoyalRoad"
    },
    "53474": {
        "wln": 149523,
        "wn": null,
        "name": "Battlefield NYC [LitRPG Apocalypse]",
        "list": "duplicates"
    },
    "53564": {
        "wln": 149618,
        "wn": null,
        "name": "Shadow of the Spyre",
        "list": "RoyalRoad"
    },
    "53587": {
        "wln": 149612,
        "wn": null,
        "name": "Hidden Paths: The Shoutout Saga",
        "list": "RoyalRoad"
    },
    "53902": {
        "wln": 150052,
        "wn": null,
        "name": "Black Onyx - Forgotten Magic",
        "list": "RoyalRoad"
    },
    "54046": {
        "wln": 150192,
        "wn": null,
        "name": "FINAL CORE : [A holy dungeon-core litRPG]",
        "list": "RoyalRoad plan to read"
    },
    "54344": {
        "wln": 150471,
        "wn": null,
        "name": "Vines",
        "list": "RoyalRoad"
    },
    "54648": {
        "wln": 150926,
        "wn": null,
        "name": "A Day in the Life of a Combat Maid [A LitRPG Short]",
        "list": "RoyalRoad completed"
    },
    "54658": {
        "wln": 150807,
        "wn": null,
        "name": "Sporemageddon",
        "list": "RoyalRoad"
    },
    "55057": {
        "wln": 152177,
        "wn": null,
        "name": "Violet: Overpowered Magic Goo",
        "list": "RoyalRoad"
    },
    "55664": {
        "wln": 152061,
        "wn": null,
        "name": "Don't Call Me a Grim Reaper!",
        "list": "RoyalRoad"
    },
    "55672": {
        "wln": 152083,
        "wn": null,
        "name": "Apocalypse Tamer",
        "list": "RoyalRoad"
    },
    "55687": {
        "wln": 152112,
        "wn": null,
        "name": "All The Skills - A Deckbuilding LitRPG",
        "list": "RoyalRoad plan to read"
    },
    "56213": {
        "wln": 152699,
        "wn": null,
        "name": "The Fox Girl From The White Plains",
        "list": "RoyalRoad"
    }
}